setup.py
rollout/__init__.py
rollout/models.py
rollout.egg-info/PKG-INFO
rollout.egg-info/SOURCES.txt
rollout.egg-info/dependency_links.txt
rollout.egg-info/requires.txt
rollout.egg-info/top_level.txt
rollout/management/__init__.py
rollout/management/commands/__init__.py
rollout/management/commands/rollout.py
rollout/templatetags/__init__.py
rollout/templatetags/rollout.py
rollout/tests/__init__.py
rollout/tests/command.py
rollout/tests/templatetags.py
tests/__init__.py
tests/manage.py
tests/settings.py